wordatlas/__init__.py
wordatlas/cli.py
wordatlas/config.py
wordatlas/logging_config.py
wordatlas/models.py
wordatlas/api/__init__.py
wordatlas/api/app.py
wordatlas/api/static/app.js
wordatlas/api/static/favicon.svg
wordatlas/api/static/index.html
wordatlas/api/static/styles.css
wordatlas/services/__init__.py
wordatlas/services/graph_builder.py
wordatlas/services/renderer.py
wordatlas/services/wordnet_service.py
wordatlas-0.1.1.dist-info/licenses/LICENSE
wordatlas-0.1.1.dist-info/METADATA
wordatlas-0.1.1.dist-info/WHEEL
wordatlas-0.1.1.dist-info/entry_points.txt
wordatlas-0.1.1.dist-info/top_level.txt
wordatlas-0.1.1.dist-info/RECORD
