Metadata-Version: 2.4
Name: wordatlas
Version: 0.1.1
Summary: Interactive semantic maps (WordNet) via CLI and web
Author: Soumyadip Sarkar
License: # License
Project-URL: Homepage, https://github.com/neuralsorcerer/WordAtlas
Project-URL: Issues, https://github.com/neuralsorcerer/WordAtlas/issues
Keywords: wordnet,nlp,graph,fastapi,cli,cytoscape
Classifier: Programming Language :: Python :: 3.9
Classifier: Programming Language :: Python :: 3.10
Classifier: Programming Language :: Python :: 3.11
Classifier: Programming Language :: Python :: 3.12
Classifier: Programming Language :: Python :: 3.13
Classifier: License :: OSI Approved :: Apache Software License
Classifier: Environment :: Console
Classifier: Environment :: Web Environment
Classifier: Intended Audience :: Developers
Classifier: Topic :: Scientific/Engineering :: Artificial Intelligence
Requires-Python: >=3.9
License-File: LICENSE
Requires-Dist: fastapi>=0.111
Requires-Dist: uvicorn[standard]>=0.29
Requires-Dist: pydantic>=2.7
Requires-Dist: typer>=0.12
Requires-Dist: rich>=13.7
Requires-Dist: nltk>=3.9
Requires-Dist: graphviz>=0.20
Requires-Dist: orjson>=3.10
Provides-Extra: dev
Requires-Dist: pytest>=8.0; extra == "dev"
Requires-Dist: httpx>=0.27; extra == "dev"
Requires-Dist: ruff>=0.6; extra == "dev"
Requires-Dist: black>=24.4; extra == "dev"
Requires-Dist: mypy>=1.10; extra == "dev"
Requires-Dist: isort>=5.13; extra == "dev"
Dynamic: license-file
